dayforcepy/__init__.py
dayforcepy/auth.py
dayforcepy/client.py
dayforcepy/config.py
dayforcepy/helper/report.py
dayforcepy/helper/report_metadata.py
dayforcepy/resources/analytics_data_connector.py
dayforcepy/resources/background_jobs.py
dayforcepy/resources/base_resource.py
dayforcepy/resources/departments.py
dayforcepy/resources/employee_properties.py
dayforcepy/resources/employees.py
dayforcepy/resources/job_assignments.py
dayforcepy/resources/location_addresses.py
dayforcepy/resources/org_units.py
dayforcepy/resources/pay_adjustments.py
dayforcepy/resources/payroll_elections.py
dayforcepy/resources/projects.py
dayforcepy/resources/work_assignments.py
dayforcepy-1.0.0.dist-info/METADATA
dayforcepy-1.0.0.dist-info/WHEEL
dayforcepy-1.0.0.dist-info/top_level.txt
dayforcepy-1.0.0.dist-info/RECORD
