Metadata-Version: 2.4
Name: dayforcepy
Version: 1.0.0
Summary: Connector for Dayforce HCM API
Requires-Python: >=3.10
Requires-Dist: pandas>=2.3.0
Requires-Dist: requests>=2.32.4
